LICENSE
MANIFEST.in
README.rst
setup.cfg
setup.py
tox.ini
django_field_editor/__init__.py
django_field_editor/admin.py
django_field_editor/apps.py
django_field_editor/fields.py
django_field_editor/models.py
django_field_editor/widgets.py
django_field_editor.egg-info/PKG-INFO
django_field_editor.egg-info/SOURCES.txt
django_field_editor.egg-info/dependency_links.txt
django_field_editor.egg-info/not-zip-safe
django_field_editor.egg-info/top_level.txt
django_field_editor/migrations/__init__.py
django_field_editor/static/json_widget/jsoneditor-minimalist.min.js
django_field_editor/static/json_widget/jsoneditor.min.css
django_field_editor/static/json_widget/jsoneditor.min.js
django_field_editor/static/json_widget/img/jsoneditor-icons.svg
django_field_editor/templates/json_editor.html