Metadata-Version: 1.0
Name: django-field-editor
Version: 0.0.3
Summary: Django field editor.
Home-page: https://github.com/kycool/django-field-editor
Author: kycool
Author-email: kycoolcool@gmail.com
License: GPL
Platform: UNKNOWN
